aibaba_ai_openai/__init__.py
aibaba_ai_openai/chat_models/__init__.py
aibaba_ai_openai/chat_models/azure.py
aibaba_ai_openai/chat_models/base.py
aibaba_ai_openai/embeddings/__init__.py
aibaba_ai_openai/embeddings/azure.py
aibaba_ai_openai/embeddings/base.py
aibaba_ai_openai/llms/__init__.py
aibaba_ai_openai/llms/azure.py
aibaba_ai_openai/llms/base.py
aibaba_ai_openai/output_parsers/__init__.py
aibaba_ai_openai/output_parsers/tools.py
aibaba_ai_openai/py.typed
aibaba_ai_openai-0.2.14.dist-info/LICENSE
aibaba_ai_openai-0.2.14.dist-info/METADATA
aibaba_ai_openai-0.2.14.dist-info/WHEEL
aibaba_ai_openai-0.2.14.dist-info/RECORD
