Metadata-Version: 2.1
Name: aibaba_ai_openai
Version: 0.2.14
Summary: An integration package connecting OpenAI and Aibaba AI
Home-page: https://github.com/aibaba-ai/aibaba-ai
License: MIT
Requires-Python: >=3.9,<4.0
Classifier: License :: OSI Approved :: MIT License
Classifier: Programming Language :: Python :: 3
Classifier: Programming Language :: Python :: 3.9
Classifier: Programming Language :: Python :: 3.10
Classifier: Programming Language :: Python :: 3.11
Classifier: Programming Language :: Python :: 3.12
Requires-Dist: aibaba_ai_core (>=0.3.27,<0.4.0)
Requires-Dist: openai (>=1.58.1,<2.0.0)
Requires-Dist: tiktoken (>=0.7,<1)
Project-URL: Repository, https://github.com/aibaba-ai/aibaba-ai
Project-URL: Release Notes, https://github.com/aibaba-ai/aibaba-ai/releases?q=tag%3A%22langchain-openai%3D%3D0%22&expanded=true
Project-URL: Source Code, https://github.com/aibaba-ai/aibaba-ai/tree/master/libs/partners/openai
